geolite2
_maxminddb_geolite2
