Metadata-Version: 1.1
Name: maxminddb-geolite2
Version: 2015.0303
Summary: Provides access to the geolite2 database.  This product includes GeoLite2 data created by MaxMind, available from http://www.maxmind.com/
Home-page: http://github.com/rr2do2/maxminddb-geolite2
Author: Arnout van Meer
Author-email: rr2do2@gmail.com
License: UNKNOWN
Platform: UNKNOWN
Classifier: Programming Language :: Python
